faceid_lib/CHANGELOG.md
faceid_lib/Makefile
faceid_lib/__init__.cpython-38-darwin.so
faceid_lib/__init__.cpython-38-x86_64-linux-gnu.so
faceid_lib/__main__.cpython-38-darwin.so
faceid_lib/__main__.cpython-38-x86_64-linux-gnu.so
faceid_lib/events/__init__.cpython-38-darwin.so
faceid_lib/events/__init__.cpython-38-x86_64-linux-gnu.so
faceid_lib/events/event_producer.cpython-38-darwin.so
faceid_lib/events/event_producer.cpython-38-x86_64-linux-gnu.so
faceid_lib/events/event_receiver.cpython-38-darwin.so
faceid_lib/events/event_receiver.cpython-38-x86_64-linux-gnu.so
faceid_lib/logger/__init__.cpython-38-darwin.so
faceid_lib/logger/__init__.cpython-38-x86_64-linux-gnu.so
faceid_lib/logger/logger_helper.cpython-38-darwin.so
faceid_lib/logger/logger_helper.cpython-38-x86_64-linux-gnu.so
faceid_lib/ratelimiter/__init__.cpython-38-darwin.so
faceid_lib/ratelimiter/__init__.cpython-38-x86_64-linux-gnu.so
faceid_lib/ratelimiter/depends.cpython-38-darwin.so
faceid_lib/ratelimiter/depends.cpython-38-x86_64-linux-gnu.so
faceid_lib/vector_similarity/__init__.cpython-38-darwin.so
faceid_lib/vector_similarity/__init__.cpython-38-x86_64-linux-gnu.so
faceid_lib/vector_similarity/v1/__init__.cpython-38-darwin.so
faceid_lib/vector_similarity/v1/__init__.cpython-38-x86_64-linux-gnu.so
faceid_lib/vector_similarity/v1/power.cpython-38-darwin.so
faceid_lib/vector_similarity/v1/power.cpython-38-x86_64-linux-gnu.so
faceid_lib/workflow/__init__.cpython-38-darwin.so
faceid_lib/workflow/__init__.cpython-38-x86_64-linux-gnu.so
faceid_lib/workflow/workflow_helper.cpython-38-darwin.so
faceid_lib/workflow/workflow_helper.cpython-38-x86_64-linux-gnu.so
faceid_lib-3.0.0.dist-info/entry_points.txt
faceid_lib-3.0.0.dist-info/WHEEL
faceid_lib-3.0.0.dist-info/METADATA
faceid_lib-3.0.0.dist-info/RECORD
